param_ctl/__init__.py
param_ctl/param_manager.py
param_ctl/param_server.py
param_ctl/static/script.js
param_ctl/static/style.css
param_ctl/templates/index.html
param_controller-0.1.6.dist-info/METADATA
param_controller-0.1.6.dist-info/WHEEL
param_controller-0.1.6.dist-info/top_level.txt
param_controller-0.1.6.dist-info/RECORD
