Metadata-Version: 2.4
Name: param-controller
Version: 0.1.6
Summary: A lightweight parameter remote controller for embedded device debugging
Home-page: https://github.com/Kori-Sama/param-ctl
Author: Kori-Sama
Author-email: Miyohashikori457@gmail.com
Classifier: Programming Language :: Python :: 3
Classifier: License :: OSI Approved :: MIT License
Classifier: Operating System :: OS Independent
Requires-Python: >=3.6
Dynamic: author
Dynamic: author-email
Dynamic: classifier
Dynamic: description
Dynamic: description-content-type
Dynamic: home-page
Dynamic: requires-python
Dynamic: summary
